alu.sv
module alu (output logic [31:0] ALUResult,
            output logic Zero,
            input logic [31:0] SrcA, SrcB,
            input logic [2:0] ALUControl);

logic [31:0] MuxOut ;

always_comb begin
  case (ALUControl)
    3'b000: MuxOut = SrcA + SrcB; // ADD
      
    3'b001: MuxOut = SrcA - SrcB; // SUB
      
    3'b010: MuxOut = SrcA & SrcB; // AND
      
    3'b011: MuxOut = SrcA | SrcB; // OR
      
    3'b100: MuxOut = SrcB; // LUI / B
      
    3'b101: MuxOut = (SrcA < SrcB) ? 32'b1 : 32'b0; // SLT
      

  endcase
  ALUResult = MuxOut;
  Zero = (MuxOut == 32'b0) ? 1'b1 : 1'b0; 
end

endmodule

alu_tb.sv
`timescale 1ns/1ps
`include "alu.sv"

module alu_tb;
logic [31:0] t_ALUResult, t_SrcA, t_SrcB;
logic [2:0] t_ALUControl;
logic t_Zero;

alu dut (t_ALUResult, t_Zero, t_SrcA, t_SrcB, t_ALUControl);

initial begin      
  $dumpfile("alu_tb.vcd"); 
  $dumpvars(0, alu_tb);
  t_ALUControl = 0; t_SrcA = 4; t_SrcB = 3;
  #10 t_ALUControl = 1; t_SrcA = 4; t_SrcB = 3;
  #10 t_ALUControl = 2; t_SrcA = 0; t_SrcB = 0;
  #10 t_ALUControl = 2; t_SrcA = 1; t_SrcB = 0;
  #10 t_ALUControl = 2; t_SrcA = 0; t_SrcB = 1;
  #10 t_ALUControl = 2; t_SrcA = 1; t_SrcB = 1;
  #10 t_ALUControl = 3; t_SrcA = 0; t_SrcB = 0;
  #10 t_ALUControl = 3; t_SrcA = 1; t_SrcB = 0;
  #10 t_ALUControl = 3; t_SrcA = 0; t_SrcB = 1;
  #10 t_ALUControl = 3; t_SrcA = 1; t_SrcB = 1;
  #10 t_ALUControl = 4; t_SrcA = 4; t_SrcB = 3;
  #10 t_ALUControl = 5; t_SrcA = 4; t_SrcB = 3;
  #10 t_ALUControl = 5; t_SrcA = 3; t_SrcB = 3;
  #10 t_ALUControl = 5; t_SrcA = 3; t_SrcB = 4;
  #10;
end

initial begin                             // Response monitor

$monitor("t_ALUResult = %d t_Zero = %d t_SrcA = %d t_SrcB = %d t_Zero = %d", 
          t_ALUResult, t_Zero, t_SrcA, t_SrcB, t_Zero);
end
endmodule

alu_tb.vcd
$date
	Sun Feb 25 10:09:23 2024
$end
$version
	Icarus Verilog
$end
$timescale
	1ps
$end
$scope module alu_tb $end
$var wire 1 ! t_Zero $end
$var wire 32 " t_ALUResult [31:0] $end
$var reg 3 # t_ALUControl [2:0] $end
$var reg 32 $ t_SrcA [31:0] $end
$var reg 32 % t_SrcB [31:0] $end
$scope module dut $end
$var wire 3 & ALUControl [2:0] $end
$var wire 32 ' SrcA [31:0] $end
$var wire 32 ( SrcB [31:0] $end
$var reg 32 ) ALUResult [31:0] $end
$var reg 32 * MuxOut [31:0] $end
$var reg 1 ! Zero $end
$upscope $end
$upscope $end
$enddefinitions $end
#0
$dumpvars
b111 *
b111 )
b11 (
b100 '
b0 &
b11 %
b100 $
b0 #
b111 "
0!
$end
#10000
b1 "
b1 )
b1 *
b1 #
b1 &
#20000
1!
b0 "
b0 )
b0 *
b0 %
b0 (
b0 $
b0 '
b10 #
b10 &
#30000
b1 $
b1 '
#40000
b1 %
b1 (
b0 $
b0 '
#50000
0!
b1 "
b1 )
b1 *
b1 $
b1 '
#60000
1!
b0 "
b0 )
b0 *
b0 %
b0 (
b0 $
b0 '
b11 #
b11 &
#70000
0!
b1 "
b1 )
b1 *
b1 $
b1 '
#80000
b1 %
b1 (
b0 $
b0 '
#90000
b1 $
b1 '
#100000
b11 "
b11 )
b11 *
b11 %
b11 (
b100 $
b100 '
b100 #
b100 &
#110000
1!
b0 "
b0 )
b0 *
b101 #
b101 &
#120000
b11 $
b11 '
#130000
0!
b1 "
b1 )
b1 *
b100 %
b100 (
