control_unit.sv
module control_unit (output logic [1:0] PCSrc, ResultSrc,
                    output logic MemWrite, ALUSrc, RegWrite,
                    output logic [2:0] ALUControl, ImmSrc,
                    input logic [31:0] Instr,
                    input logic Zero);

// Decode opcode, funct3, and funct7 from the instruction
wire [6:0] opcode = Instr[6:0];
wire [2:0] funct3 = Instr[14:12];
wire [6:0] funct7 = Instr[31:25];

always_comb begin

    // Set default values
    RegWrite = 1;
    ImmSrc = 3'b000;
    ALUSrc = 0;
    ALUControl = 3'b000; 
    MemWrite = 0;
    ResultSrc = 2'b00;
    PCSrc = 2'b00;

    case (opcode)
      7'b0110011: begin
        case (funct3)
          3'b000: ALUControl = (funct7 == 7'b010100) ? 3'b001 : 3'b000; // SUB or ADD
          3'b110: ALUControl = 3'b011; // OR
          3'b111: ALUControl = 3'b010; // AND
          3'b010: ALUControl = 3'b101; // SLT    
        endcase
      end
      7'b0010011: begin // I-Type (Imm ALU Ops)
        ALUSrc = 1;
        case (funct3)
          3'b000: ALUControl = 3'b000; // ADDI
          3'b110: ALUControl = 3'b011; // ORI
          3'b111: ALUControl = 3'b010; // ANDI
        endcase
      end
      7'b0000011: begin // LW
        ALUSrc = 1;
        ALUControl = 3'b000; 
        ResultSrc = 2'b01;
      end
      7'b0100011: begin // SW
        RegWrite = 0;
        ImmSrc = 3'b001;
        ALUSrc = 1;
        ALUControl = 3'b000; 
        MemWrite = 1;
        ResultSrc = 2'bx;
      end
      7'b1100011: begin // BEQ
        RegWrite = 0;
        ImmSrc = 3'b010;
        ALUControl = 3'b001; 
        PCSrc= 2'b01;
      end
      7'b1101111: begin // JAL
        ImmSrc = 3'b011;
        ALUSrc = 1'bx;
        ALUControl = 3'bx; 
        ResultSrc = 2'b10;
        PCSrc= 2'b01;
      end
      7'b1100111: begin // JALR
        ALUSrc = 1;
        ALUControl = 3'b000; 
        ResultSrc = 2'b10;
        PCSrc= 2'b10;
      end
      7'b0110111: begin // LUI
        ImmSrc = 3'b100;
        ALUSrc = 1;
        ALUControl = 3'b100; 
      end
    endcase
end
endmodule

control_unit_tb.sv
`timescale 1ns/1ps
`include "control_unit.sv"

module control_unit_tb;
logic [31:0] t_Instr;
logic [2:0] t_ALUControl, t_ImmSrc;
logic [1:0] t_PCSrc, t_ResultSrc;
logic t_MemWrite, t_ALUSrc, t_RegWrite, t_Zero;

control_unit dut(t_PCSrc, t_ResultSrc, t_MemWrite, t_ALUSrc, t_RegWrite, t_ALUControl, t_ImmSrc, t_Instr, t_Zero);

initial begin      
  $dumpfile("control_unit_tb.vcd");
  $dumpvars(0, control_unit_tb);
  t_Instr = 51; t_Zero = 0; // add 0000000 0000000000 000 00000 0110011
  #10 t_Instr = 671088691; t_Zero = 0; //sub 0010100 0000000000 000 00000 0110011
  #10 t_Instr = 24627; t_Zero = 0; // or 0000000 0000000000 110 00000 0110011
  #10 t_Instr = 28723; t_Zero = 0; // and 0000000 0000000000 111 00000 0110011
  #10 t_Instr = 8243; t_Zero = 0; // slt 0000000 0000000000 010 00000 0110011
  #10 t_Instr = 19; t_Zero = 0; // addi 0000000 0000000000 000 00000 0010011
  #10 t_Instr = 24595; t_Zero = 0; // ori 0000000 0000000000 110 00000 0010011
  #10 t_Instr = 28691; t_Zero = 0; // andi 0000000 0000000000 111 00000 0010011
  #10 t_Instr = 8195; t_Zero = 0; // lw 0000000 0000000000 010 00000 0000011
  #10 t_Instr = 8227; t_Zero = 0; // sw 0000000 0000000000 010 00000 0100011
  #10 t_Instr = 99; t_Zero = 0; // beq 0000000 0000000000 000 00000 1100011
  #10 t_Instr = 111; t_Zero = 0; // jal 0000000 0000000000 000 00000 1101111
  #10 t_Instr = 103; t_Zero = 0; // jalr 0000000 0000000000 000 00000 1100111
  #10 t_Instr = 55; t_Zero = 0; // lui 0000000 0000000000 000 00000 0110111
  #10;
end

initial begin                             // Response monitor

$monitor("t_PCSrc = %d t_ResultSrc = %d t_MemWrite = %d t_ALUSrc = %d t_RegWrite = %d t_ALUControl = %d t_ImmSrc = %d t_Instr = %d t_Zero = %d", 
          t_PCSrc, t_ResultSrc, t_MemWrite, t_ALUSrc, t_RegWrite, t_ALUControl, t_ImmSrc, t_Instr, t_Zero);
end
endmodule

control_unit_tb.vcd
$date
	Sun Feb 25 14:14:39 2024
$end
$version
	Icarus Verilog
$end
$timescale
	1ps
$end
$scope module control_unit_tb $end
$var wire 2 ! t_ResultSrc [1:0] $end
$var wire 1 " t_RegWrite $end
$var wire 2 # t_PCSrc [1:0] $end
$var wire 1 $ t_MemWrite $end
$var wire 3 % t_ImmSrc [2:0] $end
$var wire 1 & t_ALUSrc $end
$var wire 3 ' t_ALUControl [2:0] $end
$var reg 32 ( t_Instr [31:0] $end
$var reg 1 ) t_Zero $end
$scope module dut $end
$var wire 32 * Instr [31:0] $end
$var wire 1 ) Zero $end
$var wire 7 + opcode [6:0] $end
$var wire 7 , funct7 [6:0] $end
$var wire 3 - funct3 [2:0] $end
$var reg 3 . ALUControl [2:0] $end
$var reg 1 & ALUSrc $end
$var reg 3 / ImmSrc [2:0] $end
$var reg 1 $ MemWrite $end
$var reg 2 0 PCSrc [1:0] $end
$var reg 1 " RegWrite $end
$var reg 2 1 ResultSrc [1:0] $end
$upscope $end
$upscope $end
$enddefinitions $end
#0
$dumpvars
b0 1
b0 0
b0 /
b0 .
b0 -
b0 ,
b110011 +
b110011 *
0)
b110011 (
b0 '
0&
b0 %
0$
b0 #
1"
b0 !
$end
#10000
b1 '
b1 .
b10100 ,
b101000000000000000000000110011 (
b101000000000000000000000110011 *
#20000
b11 '
b11 .
b110 -
b0 ,
b110000000110011 (
b110000000110011 *
#30000
b10 '
b10 .
b111 -
b111000000110011 (
b111000000110011 *
#40000
b101 '
b101 .
b10 -
b10000000110011 (
b10000000110011 *
#50000
1&
b0 '
b0 .
b10011 +
b0 -
b10011 (
b10011 *
#60000
b11 '
b11 .
1&
b110 -
b110000000010011 (
b110000000010011 *
#70000
b10 '
b10 .
1&
b111 -
b111000000010011 (
b111000000010011 *
#80000
b1 !
b1 1
b0 '
b0 .
1&
b11 +
b10 -
b10000000000011 (
b10000000000011 *
#90000
1$
b1 %
b1 /
0"
bx !
bx 1
1&
b100011 +
b10000000100011 (
b10000000100011 *
#100000
b1 #
b1 0
b1 '
b1 .
b0 !
b0 1
0$
0&
b10 %
b10 /
0"
b1100011 +
b0 -
b1100011 (
b1100011 *
#110000
b10 !
b10 1
x&
b1 #
b1 0
bx '
bx .
b11 %
b11 /
1"
b1101111 +
b1101111 (
b1101111 *
#120000
b10 #
b10 0
b10 !
b10 1
b0 '
b0 .
1&
b0 %
b0 /
b1100111 +
b1100111 (
b1100111 *
#130000
b100 '
b100 .
b100 %
b100 /
b0 #
b0 0
b0 !
b0 1
1&
b110111 +
b110111 (
b110111 *
